{
  "modelVersion" : "2.3",
  "id" : "newPage",
  "name" : "newPage",
  "lastUpdate" : 1677778780889,
  "rows" : [
    [
      {
        "type" : "container",
        "dimension" : {
          "md" : 12,
          "sm" : 12,
          "xs" : 12,
          "lg" : 12
        },
        "propertyValues" : {
          "repeatedCollection" : {
            "type" : "variable"
          },
          "hidden" : {
            "type" : "constant",
            "value" : false
          },
          "cssClasses" : {
            "type" : "constant",
            "value" : ""
          },
          "dimension" : {
            "type" : "constant",
            "value" : 12
          }
        },
        "reference" : "54ff5afb-e3e6-4b26-af9b-7d91e33b7092",
        "hasValidationError" : false,
        "id" : "pbContainer",
        "description" : "Auto generate ui for business object \"company.model.Asignaturas\"",
        "rows" : [
          [
            {
              "type" : "container",
              "dimension" : {
                "xs" : 12
              },
              "propertyValues" : { },
              "reference" : "c8322969-d0af-4b15-beb7-5b3a693cb9a6",
              "hasValidationError" : false,
              "id" : "pbContainer",
              "description" : "\"company.model.Asignaturas\" object from \"asignaturas\" variable",
              "rows" : [
                [
                  {
                    "type" : "component",
                    "dimension" : {
                      "md" : 12,
                      "sm" : 12,
                      "xs" : 12,
                      "lg" : 12
                    },
                    "propertyValues" : {
                      "hidden" : {
                        "type" : "constant",
                        "value" : false
                      },
                      "level" : {
                        "type" : "constant",
                        "value" : "Level 4"
                      },
                      "cssClasses" : {
                        "type" : "constant",
                        "value" : ""
                      },
                      "text" : {
                        "type" : "interpolation",
                        "value" : "Asignaturas"
                      },
                      "alignment" : {
                        "type" : "constant",
                        "value" : "left"
                      },
                      "dimension" : {
                        "type" : "constant",
                        "value" : 12
                      }
                    },
                    "reference" : "8dc080c8-c74e-4cb2-a73e-ea19de4689c4",
                    "hasValidationError" : false,
                    "id" : "pbTitle",
                    "description" : ""
                  }
                ],
                [
                  {
                    "type" : "component",
                    "dimension" : {
                      "md" : 12,
                      "sm" : 12,
                      "xs" : 12,
                      "lg" : 12
                    },
                    "propertyValues" : {
                      "headers" : {
                        "type" : "constant",
                        "value" : [
                          "Si",
                          "Profesor Imparte",
                          "Creditos"
                        ]
                      },
                      "allowHtml" : {
                        "type" : "constant",
                        "value" : true
                      },
                      "hidden" : {
                        "type" : "constant",
                        "value" : false
                      },
                      "cssClasses" : {
                        "type" : "constant",
                        "value" : ""
                      },
                      "condensed" : {
                        "type" : "constant",
                        "value" : false
                      },
                      "bordered" : {
                        "type" : "constant",
                        "value" : false
                      },
                      "selectedRow" : {
                        "type" : "variable",
                        "value" : "asignaturas_selected"
                      },
                      "columnsKey" : {
                        "type" : "constant",
                        "value" : [
                          "si",
                          "profesorImparte",
                          "creditos"
                        ]
                      },
                      "dimension" : {
                        "type" : "constant",
                        "value" : 12
                      },
                      "content" : {
                        "type" : "expression",
                        "value" : "asignaturas"
                      },
                      "zebraStriping" : {
                        "type" : "constant",
                        "value" : true
                      }
                    },
                    "reference" : "bcd6775b-9c72-4d78-829c-c1f224dcead3",
                    "hasValidationError" : false,
                    "id" : "pbTable",
                    "description" : ""
                  }
                ],
                [
                  {
                    "type" : "container",
                    "dimension" : {
                      "md" : 1,
                      "sm" : 1,
                      "xs" : 1,
                      "lg" : 1
                    },
                    "propertyValues" : {
                      "repeatedCollection" : {
                        "type" : "variable"
                      },
                      "hidden" : {
                        "type" : "expression",
                        "value" : "!asignaturas_selected"
                      },
                      "cssClasses" : {
                        "type" : "constant",
                        "value" : ""
                      },
                      "dimension" : {
                        "type" : "constant",
                        "value" : 1
                      }
                    },
                    "reference" : "f2d45090-e90b-48d9-a44f-ac7fcc0b8f72",
                    "hasValidationError" : false,
                    "id" : "pbContainer",
                    "rows" : [
                      [ ]
                    ]
                  },
                  {
                    "type" : "container",
                    "dimension" : {
                      "md" : 11,
                      "sm" : 11,
                      "xs" : 11,
                      "lg" : 11
                    },
                    "propertyValues" : {
                      "repeatedCollection" : {
                        "type" : "variable"
                      },
                      "hidden" : {
                        "type" : "expression",
                        "value" : "!asignaturas_selected"
                      },
                      "cssClasses" : {
                        "type" : "constant",
                        "value" : ""
                      },
                      "dimension" : {
                        "type" : "constant",
                        "value" : 11
                      }
                    },
                    "reference" : "0596f125-2444-4ce7-a664-48fdcf71250b",
                    "hasValidationError" : false,
                    "id" : "pbContainer",
                    "description" : "Display \"Asignaturas\" details when a line is selected in the table above",
                    "rows" : [
                      [
                        {
                          "type" : "component",
                          "dimension" : {
                            "md" : 12,
                            "sm" : 12,
                            "xs" : 12,
                            "lg" : 12
                          },
                          "propertyValues" : {
                            "labelHidden" : {
                              "type" : "constant",
                              "value" : false
                            },
                            "hidden" : {
                              "type" : "expression",
                              "value" : "!asignaturas_selected.si"
                            },
                            "labelPosition" : {
                              "type" : "constant",
                              "value" : "top"
                            },
                            "cssClasses" : {
                              "type" : "constant",
                              "value" : ""
                            },
                            "labelWidth" : {
                              "type" : "constant",
                              "value" : 1
                            },
                            "readOnly" : {
                              "type" : "constant",
                              "value" : true
                            },
                            "label" : {
                              "type" : "interpolation",
                              "value" : "Si"
                            },
                            "placeholder" : {
                              "type" : "constant"
                            },
                            "type" : {
                              "type" : "constant",
                              "value" : "text"
                            },
                            "dimension" : {
                              "type" : "constant",
                              "value" : 12
                            },
                            "value" : {
                              "type" : "variable",
                              "value" : "asignaturas_selected.si"
                            },
                            "required" : {
                              "type" : "constant",
                              "value" : false
                            },
                            "allowHTML" : {
                              "type" : "constant",
                              "value" : false
                            },
                            "minLength" : {
                              "type" : "constant",
                              "value" : ""
                            },
                            "maxLength" : {
                              "type" : "constant",
                              "value" : ""
                            },
                            "min" : {
                              "type" : "constant"
                            },
                            "max" : {
                              "type" : "constant"
                            },
                            "step" : {
                              "type" : "constant",
                              "value" : 1
                            }
                          },
                          "reference" : "b3f0cae2-6d96-42e2-af0e-fbca49433124",
                          "hasValidationError" : false,
                          "id" : "pbInput",
                          "description" : ""
                        }
                      ],
                      [
                        {
                          "type" : "component",
                          "dimension" : {
                            "md" : 12,
                            "sm" : 12,
                            "xs" : 12,
                            "lg" : 12
                          },
                          "propertyValues" : {
                            "labelHidden" : {
                              "type" : "constant",
                              "value" : false
                            },
                            "hidden" : {
                              "type" : "expression",
                              "value" : "!asignaturas_selected.profesorImparte"
                            },
                            "labelPosition" : {
                              "type" : "constant",
                              "value" : "top"
                            },
                            "cssClasses" : {
                              "type" : "constant",
                              "value" : ""
                            },
                            "labelWidth" : {
                              "type" : "constant",
                              "value" : 1
                            },
                            "readOnly" : {
                              "type" : "constant",
                              "value" : true
                            },
                            "label" : {
                              "type" : "interpolation",
                              "value" : "Profesor Imparte"
                            },
                            "placeholder" : {
                              "type" : "constant"
                            },
                            "type" : {
                              "type" : "constant",
                              "value" : "text"
                            },
                            "dimension" : {
                              "type" : "constant",
                              "value" : 12
                            },
                            "value" : {
                              "type" : "variable",
                              "value" : "asignaturas_selected.profesorImparte"
                            },
                            "required" : {
                              "type" : "constant",
                              "value" : false
                            }
                          },
                          "reference" : "1f355492-9b41-4546-b616-c3ecac0484ec",
                          "hasValidationError" : false,
                          "id" : "pbInput",
                          "description" : ""
                        }
                      ],
                      [
                        {
                          "type" : "component",
                          "dimension" : {
                            "md" : 12,
                            "sm" : 12,
                            "xs" : 12,
                            "lg" : 12
                          },
                          "propertyValues" : {
                            "labelHidden" : {
                              "type" : "constant",
                              "value" : false
                            },
                            "hidden" : {
                              "type" : "expression",
                              "value" : "!asignaturas_selected.creditos"
                            },
                            "labelPosition" : {
                              "type" : "constant",
                              "value" : "top"
                            },
                            "cssClasses" : {
                              "type" : "constant",
                              "value" : ""
                            },
                            "labelWidth" : {
                              "type" : "constant",
                              "value" : 1
                            },
                            "readOnly" : {
                              "type" : "constant",
                              "value" : true
                            },
                            "label" : {
                              "type" : "interpolation",
                              "value" : "Creditos"
                            },
                            "placeholder" : {
                              "type" : "constant"
                            },
                            "type" : {
                              "type" : "constant",
                              "value" : "text"
                            },
                            "dimension" : {
                              "type" : "constant",
                              "value" : 12
                            },
                            "value" : {
                              "type" : "variable",
                              "value" : "asignaturas_selected.creditos"
                            },
                            "required" : {
                              "type" : "constant",
                              "value" : false
                            }
                          },
                          "reference" : "a33b1190-1e1e-4caf-bc36-e5b249b0760f",
                          "hasValidationError" : false,
                          "id" : "pbInput",
                          "description" : ""
                        }
                      ]
                    ]
                  }
                ]
              ]
            }
          ]
        ]
      }
    ]
  ],
  "assets" : [
    {
      "id" : "87d29141-e334-43bd-9993-b4fb5f47d6ff",
      "name" : "style.css",
      "type" : "css",
      "order" : 0,
      "external" : false
    },
    {
      "id" : "9a6ef330-7dea-4a9e-9a48-2d28dff07238",
      "name" : "localization.json",
      "type" : "json",
      "order" : 0,
      "external" : false
    }
  ],
  "inactiveAssets" : [ ],
  "variables" : {
    "asignaturas" : {
      "type" : "businessdata",
      "value" : [
        "{\"displayValue\":\"findByProfesorImparte [company.model.Asignaturas]\",\"businessObjectName\":\"Asignaturas\",\"query\":{\"name\":\"findByProfesorImparte\",\"displayName\":\"findByProfesorImparte\"},\"id\":\"company.model.Asignaturas\",\"filters\":[{\"name\":\"profesorImparte\",\"type\":\"STRING\",\"collection\":false,\"value\":\"A cualquier alumno que sea persona\"}],\"pagination\":{\"p\":\"0\",\"c\":\"10\"}}"
      ],
      "exposed" : false
    },
    "asignaturas_selected" : {
      "type" : "constant",
      "value" : [
        ""
      ],
      "exposed" : false
    }
  },
  "hasValidationError" : false,
  "uuid" : "57b7b9cd-770c-4d3c-96c4-511b6386f09b",
  "type" : "page",
  "description" : "Page generated with Bonita UI designer"
}